LICENSE
MANIFEST.in
README.rst
setup.cfg
setup.py
tpHoudiniLib/__init__.py
tpHoudiniLib/__logging__.ini
tpHoudiniLib/__version__.py
tpHoudiniLib/loader.py
tpHoudiniLib/core/__init__.py
tpHoudiniLib/core/dcc.py
tpHoudiniLib/core/gui.py
tpHoudiniLib/core/helpers.py
tpHoudiniLib/core/menu.py
tpHoudiniLib/core/shelf.py
tphoudinilib.egg-info/PKG-INFO
tphoudinilib.egg-info/SOURCES.txt
tphoudinilib.egg-info/dependency_links.txt
tphoudinilib.egg-info/not-zip-safe
tphoudinilib.egg-info/requires.txt
tphoudinilib.egg-info/top_level.txt