Metadata-Version: 2.1
Name: tphoudinilib
Version: 0.0.5
Summary: Houdini implementation for tpDccLib and tpQtLib. Utils functions to work with Maya Python APIs.
Home-page: https://github.com/tpoveda/tpMayaLib
Author: Tomas Poveda
Author-email: tpovedatd@gmail.com
License: MIT
Platform: UNKNOWN
Provides-Extra: dev
Provides-Extra: test
